README.md
setup.cfg
setup.py
loglette/__info__.py
loglette/__init__.py
loglette/__main__.py
loglette/changelog.py
loglette/utils.py
loglette/version.py
loglette.egg-info/PKG-INFO
loglette.egg-info/SOURCES.txt
loglette.egg-info/dependency_links.txt
loglette.egg-info/entry_points.txt
loglette.egg-info/requires.txt
loglette.egg-info/top_level.txt
loglette.egg-info/zip-safe
loglette/formatter/__init__.py
loglette/formatter/html.py
loglette/formatter/markdown.py
loglette/formatter/special.py
loglette/parser/__init__.py
loglette/parser/loglette/__init__.py
loglette/parser/loglette/parser.py
loglette/parser/loglette/pattern.py
loglette/parser/markdown/__init__.py
loglette/parser/markdown/parser.py
loglette/parser/markdown/pattern.py