Metadata-Version: 2.1
Name: loglette
Version: 0.1.0
Summary: A changelog parser
Home-page: https://github.com/siku2/Loglette
Author: siku2
Author-email: siku2@outlook.com
License: MIT License
